bahasakita/__init__.py
bahasakita/__main__.py
bahasakita/cli.py
bahasakita/data_engineer/__init__.py
bahasakita/data_engineer/dataset.py
bahasakita/data_engineer/help.py
bahasakita/data_engineer/t.py
bahasakitasemua-0.0.0.dist-info/METADATA
bahasakitasemua-0.0.0.dist-info/WHEEL
bahasakitasemua-0.0.0.dist-info/entry_points.txt
bahasakitasemua-0.0.0.dist-info/top_level.txt
bahasakitasemua-0.0.0.dist-info/RECORD
