Metadata-Version: 2.1
Name: bahasakitasemua
Version: 0.0.0
Summary: Bahasa Kita Engineer Recruitment Test Repository
Home-page: https://github.com/bahasakita
Author: Tirtadwipa Manunggal
Author-email: tirtadwipa.manunggal@gmail.com
License: BSD 3-Clause License
Platform: UNKNOWN
Classifier: License :: OSI Approved :: BSD License
Classifier: Programming Language :: Python :: 3
Classifier: Programming Language :: Python :: 3.2
Classifier: Programming Language :: Python :: 3.3
Classifier: Programming Language :: Python :: 3.4
Classifier: Programming Language :: Python :: 3.5
Requires-Dist: click (==6.7)
Requires-Dist: colorama (==0.3.9)
Requires-Dist: dill (==0.2.7.1)
Requires-Dist: numpy (==1.14.1)
